cdk_stack_resource_rename/__init__.py
cdk_stack_resource_rename/py.typed
cdk_stack_resource_rename/_jsii/__init__.py
cdk_stack_resource_rename/_jsii/cdk-stack-resource-rename@0.0.23.jsii.tgz
cdk_stack_resource_rename-0.0.23.dist-info/LICENSE
cdk_stack_resource_rename-0.0.23.dist-info/METADATA
cdk_stack_resource_rename-0.0.23.dist-info/WHEEL
cdk_stack_resource_rename-0.0.23.dist-info/top_level.txt
cdk_stack_resource_rename-0.0.23.dist-info/RECORD
